blti/VERSION
blti/__init__.py
blti/canvas-lti.xml
blti/config.py
blti/cookie.py
blti/cookies_allowed_check.py
blti/exceptions.py
blti/launch_redirect.py
blti/middleware.py
blti/mock_data.py
blti/oidc_login.py
blti/performance.py
blti/redirect.py
blti/request.py
blti/roles.py
blti/runtests.py
blti/urls.py
blti/validators.py
blti/management/__init__.py
blti/management/commands/__init__.py
blti/management/commands/generate_credentials.py
blti/models/__init__.py
blti/models/base.py
blti/models/canvas.py
blti/resources/lti1p3/file/jwt.json
blti/templates/blti/401.html
blti/templates/blti/500.html
blti/templates/blti/base.html
blti/templates/blti/raw.html
blti/templates/blti/develop/launch.html
blti/templates/blti/develop/prepare.html
blti/tests/__init__.py
blti/tests/settings.py
blti/tests/test_blti_1p1.py
blti/tests/test_lti_1p3.py
blti/tests/test_models.py
blti/tests/test_views.py
blti/tests/urls.py
blti/views/__init__.py
blti/views/base.py
blti/views/develop.py
blti/views/jwks.py
blti/views/launch.py
blti/views/login.py
blti/views/raw.py
blti/views/rest_dispatch.py
django_blti-3.0.17.dist-info/licenses/LICENSE
django_blti-3.0.17.dist-info/METADATA
django_blti-3.0.17.dist-info/WHEEL
django_blti-3.0.17.dist-info/top_level.txt
django_blti-3.0.17.dist-info/RECORD
