Metadata-Version: 2.4
Name: django-blti
Version: 3.0.17
Summary: A Django Application on which to build IMS BLTI Tool Providers
Home-page: https://github.com/uw-it-aca/django-blti
Author: UW-IT Student & Educational Technology Services
Author-email: aca-it@uw.edu
License: Apache License, Version 2.0
Classifier: Environment :: Web Environment
Classifier: Framework :: Django
Classifier: Intended Audience :: Developers
Classifier: License :: OSI Approved :: Apache Software License
Classifier: Operating System :: OS Independent
Classifier: Programming Language :: Python
License-File: LICENSE
Requires-Dist: django
Requires-Dist: pylti1p3==2.0.0
Requires-Dist: oauthlib
Requires-Dist: cryptography
Requires-Dist: pycryptodome
Requires-Dist: jwcrypto
Requires-Dist: mock
Dynamic: author
Dynamic: author-email
Dynamic: classifier
Dynamic: description
Dynamic: home-page
Dynamic: license
Dynamic: license-file
Dynamic: requires-dist
Dynamic: summary
